{
    "config": {
        "map_no": "3",
        "horizon": "80",
        "speed_horizon_factor": "3.0",
        "lon_interval": "10.0",
        "lat_interval": "1.75",
        "road_width": "3.5",
        "infinity_cost": "100000000",
        "sampling_step": "0.1",
        "k_thr": "0.172",
        "ego_width": "1.84",
        "ego_length": "4.86",
        "s0": 21.66626265332119,
        "l0": "5.75",
        "theta0": "1.5707963267",
        "v0": 14.971130315926809,
        "speed_limit": "16.6",
        "k_limit": "5.0",
        "a_max_soft": "0.98",
        "a_min_soft": "-2.94",
        "pena_max_latg": "5.0",
        "pena_latg": "3000",
        "pena_spd": "250",
        "pena_a_max": "20",
        "pena_a_min": "20",
        "pena_curv_rate": "20",
        "latg_max_soft": "2.94",
        "curve_rate_limit": "1",
        "time_step": "0.1",
        "lane_cost_factor": "1.5",
        "map_type": "1",
        "dynamic_obstacle_lethal_cost": "100000000",
        "dynamic_obstacle_high_cost": "10000",
        "minimum_horizon": "30",
        "total_time_weight": "1.0",
        "total_dist_weight": "1.0",
        "max_eval_trajs": "200000",
        "pena_low_speed": "0",
        "same_acc_bonus": "-10",
        "auto_close_on_crash": "0",
        "auto_close_on_reach_the_objective": "1",
        "auto_close_x_position": "-10",
        "auto_close_y_position": "120",
        "straight_map_length": "100",
        "straight_map_roads": "2"
    },
    "static_obs": [],
    "traffic_signal": [
        {
            "start_s": 74.18286619038167,
            "end_s": 93.9633251911639,
            "green_time": 6.509220660067528,
            "yellow_time": 1.0409609923732566,
            "red_time": 2.752672631528556
        }
    ],
    "dynamic_obs": [
        {
            "pos_x": "-5.75",
            "pos_y": 40.73687865698987,
            "dir": "1.5707963267",
            "width": "1.8",
            "length": "4.8",
            "velo": 8.130929768897623,
            "acc": 0.5018429223365887,
            "start_time": 0.0
        },
        {
            "pos_x": "-1.75",
            "pos_y": 11.11124652770412,
            "dir": "1.5707963267",
            "width": "1.8",
            "length": "4.8",
            "velo": 15.781069310970773,
            "acc": 1.4332101046248988,
            "start_time": 0.6272468721891016
        },
        {
            "pos_x": "1.75",
            "pos_y": 86.78922754598184,
            "dir": "-1.5707963267",
            "width": "1.8",
            "length": "4.8",
            "velo": 12.195310025899996,
            "acc": 1.2285015878424834,
            "start_time": 0.8498683700173917
        }
    ]
}