{
    "config": {
        "map_no": "3",
        "horizon": "80",
        "speed_horizon_factor": "3.0",
        "lon_interval": "10.0",
        "lat_interval": "1.75",
        "road_width": "3.5",
        "infinity_cost": "100000000",
        "sampling_step": "0.1",
        "k_thr": "0.172",
        "ego_width": "1.84",
        "ego_length": "4.86",
        "s0": 26.620127344279382,
        "l0": "5.75",
        "theta0": "1.5707963267",
        "v0": 12.005671465584774,
        "speed_limit": "16.6",
        "k_limit": "5.0",
        "a_max_soft": "0.98",
        "a_min_soft": "-2.94",
        "pena_max_latg": "5.0",
        "pena_latg": "3000",
        "pena_spd": "250",
        "pena_a_max": "20",
        "pena_a_min": "20",
        "pena_curv_rate": "20",
        "latg_max_soft": "2.94",
        "curve_rate_limit": "1",
        "time_step": "0.1",
        "lane_cost_factor": "1.5",
        "map_type": "1",
        "dynamic_obstacle_lethal_cost": "100000000",
        "dynamic_obstacle_high_cost": "10000",
        "minimum_horizon": "30",
        "total_time_weight": "1.0",
        "total_dist_weight": "1.0",
        "max_eval_trajs": "200000",
        "pena_low_speed": "0",
        "same_acc_bonus": "-10",
        "auto_close_on_crash": "0",
        "auto_close_on_reach_the_objective": "1",
        "auto_close_x_position": "-10",
        "auto_close_y_position": "120",
        "straight_map_length": "100",
        "straight_map_roads": "2"
    },
    "static_obs": [],
    "traffic_signal": [
        {
            "start_s": 73.1308119351126,
            "end_s": 94.08181322876766,
            "green_time": 8.642778469828173,
            "yellow_time": 1.98099281382284,
            "red_time": 2.3800278957685945
        }
    ],
    "dynamic_obs": [
        {
            "pos_x": "-5.75",
            "pos_y": 45.87163979575399,
            "dir": "1.5707963267",
            "width": "1.8",
            "length": "4.8",
            "velo": 6.4830552198950535,
            "acc": 1.2929206317846433,
            "start_time": 0.0
        },
        {
            "pos_x": "-1.75",
            "pos_y": 5.946935068761084,
            "dir": "1.5707963267",
            "width": "1.8",
            "length": "4.8",
            "velo": 15.453236097192661,
            "acc": 2.918994224524143,
            "start_time": 1.6260229234225374
        },
        {
            "pos_x": "1.75",
            "pos_y": 87.35362362018569,
            "dir": "-1.5707963267",
            "width": "1.8",
            "length": "4.8",
            "velo": 5.535454824253822,
            "acc": 2.1843979570070875,
            "start_time": 1.8091330792184817
        }
    ]
}