{
    "config": {
        "map_no": "3",
        "horizon": "80",
        "speed_horizon_factor": "3.0",
        "lon_interval": "10.0",
        "lat_interval": "1.75",
        "road_width": "3.5",
        "infinity_cost": "100000000",
        "sampling_step": "0.1",
        "k_thr": "0.172",
        "ego_width": "1.84",
        "ego_length": "4.86",
        "s0": 24.83848312964735,
        "l0": "5.75",
        "theta0": "1.5707963267",
        "v0": 13.93872754572249,
        "speed_limit": "16.6",
        "k_limit": "5.0",
        "a_max_soft": "0.98",
        "a_min_soft": "-2.94",
        "pena_max_latg": "5.0",
        "pena_latg": "3000",
        "pena_spd": "250",
        "pena_a_max": "20",
        "pena_a_min": "20",
        "pena_curv_rate": "20",
        "latg_max_soft": "2.94",
        "curve_rate_limit": "1",
        "time_step": "0.1",
        "lane_cost_factor": "1.5",
        "map_type": "1",
        "dynamic_obstacle_lethal_cost": "100000000",
        "dynamic_obstacle_high_cost": "10000",
        "minimum_horizon": "30",
        "total_time_weight": "1.0",
        "total_dist_weight": "1.0",
        "max_eval_trajs": "200000",
        "pena_low_speed": "0",
        "same_acc_bonus": "-10",
        "auto_close_on_crash": "0",
        "auto_close_on_reach_the_objective": "1",
        "auto_close_x_position": "-10",
        "auto_close_y_position": "120",
        "straight_map_length": "100",
        "straight_map_roads": "2"
    },
    "static_obs": [],
    "traffic_signal": [
        {
            "start_s": 71.360465092912,
            "end_s": 91.32442089075991,
            "green_time": 5.952017556253093,
            "yellow_time": 1.86884759438454,
            "red_time": 2.4965571243592146
        }
    ],
    "dynamic_obs": [
        {
            "pos_x": "-5.75",
            "pos_y": 48.22116681609562,
            "dir": "1.5707963267",
            "width": "1.8",
            "length": "4.8",
            "velo": 7.0228720921266286,
            "acc": 2.4993548515218897,
            "start_time": 0.0
        },
        {
            "pos_x": "-1.75",
            "pos_y": 14.852799125570657,
            "dir": "1.5707963267",
            "width": "1.8",
            "length": "4.8",
            "velo": 14.24144305403253,
            "acc": 1.4122193121627427,
            "start_time": 1.0284265955549683
        },
        {
            "pos_x": "1.75",
            "pos_y": 48.68704607606628,
            "dir": "-1.5707963267",
            "width": "1.8",
            "length": "4.8",
            "velo": 10.14047475538174,
            "acc": 1.6777089562518832,
            "start_time": 1.9490227282443766
        }
    ]
}