{
    "config": {
        "map_no": "3",
        "horizon": "80",
        "speed_horizon_factor": "3.0",
        "lon_interval": "10.0",
        "lat_interval": "1.75",
        "road_width": "3.5",
        "infinity_cost": "100000000",
        "sampling_step": "0.1",
        "k_thr": "0.172",
        "ego_width": "1.84",
        "ego_length": "4.86",
        "s0": 25.46862308813548,
        "l0": "5.75",
        "theta0": "1.5707963267",
        "v0": 15.735602245291574,
        "speed_limit": "16.6",
        "k_limit": "5.0",
        "a_max_soft": "0.98",
        "a_min_soft": "-2.94",
        "pena_max_latg": "5.0",
        "pena_latg": "3000",
        "pena_spd": "250",
        "pena_a_max": "20",
        "pena_a_min": "20",
        "pena_curv_rate": "20",
        "latg_max_soft": "2.94",
        "curve_rate_limit": "1",
        "time_step": "0.1",
        "lane_cost_factor": "1.5",
        "map_type": "1",
        "dynamic_obstacle_lethal_cost": "100000000",
        "dynamic_obstacle_high_cost": "10000",
        "minimum_horizon": "30",
        "total_time_weight": "1.0",
        "total_dist_weight": "1.0",
        "max_eval_trajs": "200000",
        "pena_low_speed": "0",
        "same_acc_bonus": "-10",
        "auto_close_on_crash": "0",
        "auto_close_on_reach_the_objective": "1",
        "auto_close_x_position": "-10",
        "auto_close_y_position": "120",
        "straight_map_length": "100",
        "straight_map_roads": "2"
    },
    "static_obs": [],
    "traffic_signal": [
        {
            "start_s": 70.54850718921178,
            "end_s": 92.50890962495725,
            "green_time": 6.235121616915114,
            "yellow_time": 1.6030295911782855,
            "red_time": 2.9707206044850243
        }
    ],
    "dynamic_obs": [
        {
            "pos_x": "-5.75",
            "pos_y": 38.68639046351402,
            "dir": "1.5707963267",
            "width": "1.8",
            "length": "4.8",
            "velo": 4.387688136030837,
            "acc": 2.4765441609430305,
            "start_time": "0"
        },
        {
            "pos_x": "-1.75",
            "pos_y": 19.178482179796372,
            "dir": "1.5707963267",
            "width": "1.8",
            "length": "4.8",
            "velo": 10.90944499154907,
            "acc": 2.7953482543214365,
            "start_time": 1.4456800966935077
        },
        {
            "pos_x": "1.75",
            "pos_y": 55.08052213368167,
            "dir": "-1.5707963267",
            "width": "1.8",
            "length": "4.8",
            "velo": 7.834912204255203,
            "acc": 2.8366305137421106,
            "start_time": 1.3327450758588626
        }
    ]
}